soarsdk/__init__.py
soarsdk/client.py
soarsdk/exceptions.py
soarsdk/objects.py
soarsdk-1.0.1.dist-info/METADATA
soarsdk-1.0.1.dist-info/WHEEL
soarsdk-1.0.1.dist-info/top_level.txt
soarsdk-1.0.1.dist-info/RECORD
