Metadata-Version: 2.1
Name: soarsdk
Version: 1.0.1
Summary: API Wrapper and Objects for Splunk SOAR
Author-email: Tyler Chuba <tylerchuba@gmail.com>
Project-URL: repository, https://github.com/tylerjchuba/soarsdk
Requires-Python: >=3.9
Requires-Dist: requests
Requires-Dist: colorama
